odoo/addons/base_rest_auth_jwt/README.rst
odoo/addons/base_rest_auth_jwt/__init__.py
odoo/addons/base_rest_auth_jwt/__manifest__.py
odoo/addons/base_rest_auth_jwt/apispec/__init__.py
odoo/addons/base_rest_auth_jwt/apispec/rest_method_security_plugin.py
odoo/addons/base_rest_auth_jwt/components/__init__.py
odoo/addons/base_rest_auth_jwt/components/auth_jwt_component_context_provider.py
odoo/addons/base_rest_auth_jwt/components/service.py
odoo/addons/base_rest_auth_jwt/i18n/base_rest_auth_jwt.pot
odoo/addons/base_rest_auth_jwt/readme/CONTRIBUTORS.rst
odoo/addons/base_rest_auth_jwt/readme/DESCRIPTION.rst
odoo/addons/base_rest_auth_jwt/static/description/icon.png
odoo/addons/base_rest_auth_jwt/static/description/index.html
odoo14_addon_base_rest_auth_jwt-14.0.1.1.0.dist-info/METADATA
odoo14_addon_base_rest_auth_jwt-14.0.1.1.0.dist-info/WHEEL
odoo14_addon_base_rest_auth_jwt-14.0.1.1.0.dist-info/top_level.txt
odoo14_addon_base_rest_auth_jwt-14.0.1.1.0.dist-info/RECORD
