Metadata-Version: 2.1
Name: odoo14-addon-base-rest-auth-jwt
Version: 14.0.1.1.0
Summary: Base Rest: Add support for the auth_jwt security policy into the openapi documentation
Home-page: https://github.com/OCA/rest-framework
Author: ACSONE SA/NV,Odoo Community Association (OCA)
Author-email: support@odoo-community.org
License: LGPL-3
Platform: UNKNOWN
Classifier: Programming Language :: Python
Classifier: Framework :: Odoo
Classifier: License :: OSI Approved :: GNU Lesser General Public License v3 (LGPLv3)
Requires-Python: >=3.6
Requires-Dist: apispec (>=4.0.0)
Requires-Dist: odoo14-addon-auth-jwt
Requires-Dist: odoo14-addon-base-rest
Requires-Dist: odoo (<14.1dev,>=14.0a)
